MANIFEST.in
README.rst
setup.cfg
setup.py
flixster/__init__.py
flixster/client.py
flixster.egg-info/PKG-INFO
flixster.egg-info/SOURCES.txt
flixster.egg-info/dependency_links.txt
flixster.egg-info/requires.txt
flixster.egg-info/top_level.txt
flixster/query/__init__.py
flixster/query/parameter_builders.py