Metadata-Version: 1.1
Name: flixster
Version: 0.0.2
Summary: Flixster Client
Home-page: https://github.com/jaebradley/flixster
Author: Jae Bradley
Author-email: jae.b.bradley@gmail.com
License: UNKNOWN
Download-URL: https://github.com/jaebradley/flixster/tarball/0.1
Keywords: flixster,movies
Platform: UNKNOWN
